gekkota/__init__.py
gekkota/annotations.py
gekkota/args.py
gekkota/assignment.py
gekkota/block.py
gekkota/classes.py
gekkota/comments.py
gekkota/constants.py
gekkota/control_flow.py
gekkota/core.py
gekkota/exceptions.py
gekkota/expression.py
gekkota/functions.py
gekkota/generator_expr.py
gekkota/imports.py
gekkota/operator_expr.py
gekkota/pattern_matching.py
gekkota/py.typed
gekkota/sequences.py
gekkota/small_stmt.py
gekkota/to_expression.py
gekkota/utils.py
gekkota/values.py
gekkota/wscomp.py
gekkota-0.7.0.dist-info/LICENSE
gekkota-0.7.0.dist-info/METADATA
gekkota-0.7.0.dist-info/WHEEL
gekkota-0.7.0.dist-info/RECORD
