Metadata-Version: 2.1
Name: gekkota
Version: 0.7.0
Summary: Python code-generation for Python
Home-page: https://github.com/courage-tci/gekkota
License: MIT
Keywords: codegen
Author: Dmitry Gritsenko
Author-email: k01419q45@ya.ru
Requires-Python: >=3.8,<4.0
Classifier: License :: OSI Approved :: MIT License
Classifier: Programming Language :: Python :: 3
Classifier: Programming Language :: Python :: 3.8
Classifier: Programming Language :: Python :: 3.9
Classifier: Programming Language :: Python :: 3.10
Classifier: Programming Language :: Python :: 3.11
Classifier: Programming Language :: Python :: 3.12
Requires-Dist: typing-extensions (>=4.4.0,<5.0.0)
Requires-Dist: wordstreamer (>=0.1.3,<0.2.0)
Project-URL: Repository, https://github.com/courage-tci/gekkota
